parallel_pandas/__init__.py
parallel_pandas/main.py
parallel_pandas/core/__init__.py
parallel_pandas/core/_numba.py
parallel_pandas/core/parallel_dataframe.py
parallel_pandas/core/parallel_groupby.py
parallel_pandas/core/parallel_series.py
parallel_pandas/core/parallel_window.py
parallel_pandas/core/progress_imap.py
parallel_pandas/core/tools.py
parallel_pandas-0.7.dist-info/licenses/LICENSE
parallel_pandas-0.7.dist-info/WHEEL
parallel_pandas-0.7.dist-info/METADATA
parallel_pandas-0.7.dist-info/RECORD
