Metadata-Version: 2.4
Name: parallel-pandas
Version: 0.7
Summary: Parallel processing on pandas with progress bars
Author-email: Dubovik Pavel <geometryk@gmail.com>
Requires-Python: >=3.7
License-File: LICENSE
Requires-Dist: pandas>=1.4.0
Requires-Dist: dill
Requires-Dist: psutil
Requires-Dist: tqdm
Requires-Dist: scipy
Requires-Dist: numba ; extra == "numba"
Project-URL: Homepage, https://github.com/dubovikmaster/parallel-pandas
Provides-Extra: numba
